{
  "eventId": "6a86830f-d726-ded9-3b19-c376002719c1",
  "url": "https://thedinosaurthatpoopedlive.com/",
  "title": "The Dinosaur that Pooped LIVE | UK Tour 2025",
  "structured": {
    "description": "BRIGHTON\nTHEATRE ROYAL\nJanuary 25, 2026\nBUY TICKETS Thanks!",
    "priceText": "",
    "ageText": "",
    "openingHoursText": "",
    "addressText": "",
    "extractedHours": "",
    "extractedAge": "ager lurking, nothing goes to plan.\nWill the band perform?\nWill Danny rock out?\nOr will Dino’s rumbling tummy save the day?\nAdapted from the number 1 best-selling books by Tom Fletcher and Dougie Poynter, the whole family will have a poopy good time enjoying a brand new story for the stage.\nFeaturing new songs by Tom and Dougie, a lot of laughs and a whole lot of poo!\nProduced by Mark Thompson Produc",
    "extractedPrice": "TICKETS Thanks!\nTom Fletcher and Dougie Poynter's The Dinosaur that Pooped comes to theatres on a nationwide tour.\nBRIGHTON\nTHEATRE ROYAL\nJanuary 25, 2026\nBUY TICKETS Thanks!\n/\nTom Fletcher and Dougie Poynter’s The Dinosaur that Pooped is on tour in 2025!\nWhen Danny and Dino’s favourite rock band are playing their last ever concert, they go on a quest to get the last two tickets. But with a villainous band manager lurking, nothing goes to plan.\nWill the band perform?\nWill Danny rock out?\nOr will Dino’",
    "extractedDescription": "",
    "jsonLdEvents": []
  },
  "text": "BRIGHTON\nTHEATRE ROYAL\nJanuary 25, 2026\nBUY TICKETS Thanks!\nTom Fletcher and Dougie Poynter's The Dinosaur that Pooped comes to theatres on a nationwide tour.\nBRIGHTON\nTHEATRE ROYAL\nJanuary 25, 2026\nBUY TICKETS Thanks!\n/\nTom Fletcher and Dougie Poynter’s The Dinosaur that Pooped is on tour in 2025!\nWhen Danny and Dino’s favourite rock band are playing their last ever concert, they go on a quest to get the last two tickets. But with a villainous band manager lurking, nothing goes to plan.\nWill the band perform?\nWill Danny rock out?\nOr will Dino’s rumbling tummy save the day?\nAdapted from the number 1 best-selling books by Tom Fletcher and Dougie Poynter, the whole family will have a poopy good time enjoying a brand new story for the stage.\nFeaturing new songs by Tom and Dougie, a lot of laughs and a whole lot of poo!\nProduced by Mark Thompson Productions Limited and Directed by Miranda Larson.\nTOUR DATES\nBRIGHTON\nTHEATRE ROYAL\nJanuary 25, 2026\nBUY TICKETS Thanks!\nBUTLINS\nBOGNOR REGIS\nJanuary 28, 2026\nBUY TICKETS Thanks!\nNOTTINGHAM\nPLAYHOUSE\nJanuary 31, 2026\nBUY TICKETS Thanks!\nRICHMOND\nRICHMOND THEATRE\nFebruary 01, 2026\nBUY TICKETS Thanks!\nBUTLINS\nSKEGNESS\nFebruary 03, 2026\nBUY TICKETS Thanks!\nBUTLINS\nMINEHEAD\nFebruary 05, 2026\nBUY TICKETS Thanks!\nLINCOLN\nTHEATRE ROYAL\nFebruary 08, 2026\nBUY TICKETS Thanks!\nRUNCORN\nBRINDLEY\nFebruary 14, 2026\nBUY TICKETS Thanks!\nNEW BRIGHTON\nFLORAL PAVILION\nFebruary 16, 2026\nBUY TICKETS Thanks!\nLOWTHER\nPAVILION THEATRE\nFebruary 17, 2026\nBUY TICKETS Thanks!\nNEWPORT\nRIVERFRONT\nFebruary 18, 2026\nBUY TICKETS Thanks!\nREDDITCH\nPALACE THEATRE\nFebruary 19, 2026\nBUY TICKETS Thanks!\nHARLOW\nPLAYHOUSE\nFebruary 20, 2026\nBUY TICKETS Thanks!\nKINGS LYNN\nCORN EXCHANGE\nFebruary 22, 2026\nBUY TICKETS Thanks!\nSWANSEA\nGRAND\nFebruary 24, 2026\nBUY TICKETS Thanks!\nWOKING\nNEW VICTORIA THEATRE\nMarch 01, 2026\nBUY TICKETS Thanks!\nBUTLINS\nSKEGNESS\nMarch 03, 2026\nBUY TICKETS Thanks!\nCHELMSFORD\nCHELMSFORD THEATRES\nMarch 08, 2026\nBUY TICKETS Thanks!\nBUTLINS\nBOGNOR REGIS\nMarch 11, 2026\nBUY TICKETS Thanks!\nLONDON\nPENTLAND THEATRE\nMarch 14, 2026\nBUY TICKETS Thanks!\nHAYES\nBECK THEATRE\nMarch 15, 2026\nBUY TICKETS Thanks!\nBUTLINS\nMINEHEAD\nMarch 19, 2026\nBUY TICKETS Thanks!\nSOUTH SHIELDS\nCUSTOM HOUSE\nMarch 21, 2026\nBUY TICKETS Thanks!\nMANCHESTER\nOPERA HOUSE\nMarch 22, 2026\nBUY TICKETS Thanks!\nNEWBURY\nCORN EXCHANGE\nMarch 28, 2026\nBUY TICKETS Thanks!\nWAKEFIELD\nTHEATRE ROYAL\nMarch 31, 2026\nBUY TICKETS Thanks!\nBATH\nFORUM\nApril 07, 2026\nBUY TICKETS Thanks!\nBURY ST EDMUNDS\nAPEX\nApril 08, 2026\nBUY TICKETS Thanks!\nEASTBOURNE\nEASTBOURNE THEATRES\nApril 12, 2026\nBUY TICKETS Thanks!\nSUNDERLAND\nFIRE STATION\nApril 14, 2026\nBUY TICKETS Thanks!\nGLASGOW\nTHEATRE ROYAL\nApril 19, 2026\nBUY TICKETS Thanks!\nBLACKPOOL\nGRAND THEATRE\nMay 03, 2026\nBUY TICKETS Thanks!\nRAMSGATE\nGRANVILLE THEATRE\nMay 23, 2026\nBUY TICKETS Thanks!\nBRIERLEY HILL\nBRIERLEY HILL CIVIC\nMay 24, 2026\nBUY TICKETS Thanks!\nLIVERPOOL\nEVERYMAN & PLAYHOUSE\nMay 26, 2026\nBUY TICKETS Thanks!\nLIVERPOOL\nEVERYMAN & PLAYHOUSE\nMay 27, 2026\nBUY TICKETS Thanks!\nLIVERPOOL\nEVERYMAN & PLAYHOUSE\nMay 28, 2026\nBUY TICKETS Thanks!\nLIVERPOOL\nEVERYMAN & PLAYHOUSE\nMay 29, 2026\nBUY TICKETS Thanks!\nLIVERPOOL\nEVERYMAN & PLAYHOUSE\nMay 30, 2026\nBUY TICKETS Thanks!\nWORCESTER\nSWAN THEATRE\nJune 06, 2026\nBUY TICKETS Thanks!\nCARLISLE\nSANDS CENTRE\nJune 13, 2026\nBUY TICKETS Thanks!\nYORK\nGRAND OPERA\nJune 14, 2026\nBUY TICKETS Thanks!\nGUILDFORD\n​G LIVE\nJune 20, 2026\nBUY TICKETS Thanks!\nCRAWLEY\nTHE HAWTH\nJune 28, 2026\nBUY TICKETS Thanks!\nCARDIFF\nNEW THEATRE\nJuly 05, 2026\nBUY TICKETS Thanks!\nSTAFFORD\nGATEHOUSE\nJuly 22, 2026\nBUY TICKETS Thanks!\nFAREHAM\nFAREHAM LIVE\nJuly 24, 2026\nBUY TICKETS Thanks!\nST HELENS\nTHEATRE ROYAL\nJuly 26, 2026\nBUY TICKETS Thanks!\nBRIDLINGTON\nSPA\nJuly 28, 2026\nBUY TICKETS Thanks!\nABERDEEN\nTIVOLI THEATRE\nJuly 30, 2026\nBUY TICKETS Thanks!\nBASILDON\nTOWNGATE THEATRE\nAugust 02, 2026\nBUY TICKETS Thanks!\nCANTERBURY\nMALTHOUSE THEATRE\nAugust 10, 2026\nBUY TICKETS Thanks!\nHUNSTANTON\nPRINCESS THEATRE\nAugust 16, 2026\nBUY TICKETS Thanks!\nHIGH WYCOMBE\nWYCOMBE SWAN\nAugust 22, 2026\nBUY TICKETS Thanks!\nSOUTHEND\nPALACE THEATRE\nAugust 23, 2026\nBUY TICKETS Thanks!\nGRIMSBY\nAUDITORIUM\nAugust 25, 2026\nBUY TICKETS Thanks!\nDARLINGTON\nHIPPODROME\nAugust 26, 2026\nBUY TICKETS Thanks!\nSWINDON\nWYVERN THEATRE\nAugust 29, 2026\nBUY TICKETS Thanks!\nWELLINGBOROUGH\nTHE CASTLE\nAugust 30, 2026\nBUY TICKETS Thanks!\nWELLINGBOROUGH\nCASTLE THEATRE\nAugust 30, 2026\nBUY TICKETS Thanks!\nDUNSTABLE\nGROVE THEATRE\nSeptember 06, 2026\nBUY TICKETS Thanks!\nBUTLINS\nMINEHEAD\nSeptember 24, 2026\nBUY TICKETS Thanks!\nBUTLINS\nBOGNOR REGIS\nSeptember 30, 2026\nBUY TICKETS Thanks!\nBUTLINS\nSKEGNESS\nOctober 06, 2026\nBUY TICKETS Thanks!\nBASINGSTOKE\nTHE HAYMARKET\nOctober 28, 2026\nBUY TICKETS Thanks!\nBIRMINGHAM\nTOWN HALL\nNovember 08, 2026\nBUY TICKETS Thanks!\nMORE DATES COMING SOON\nCheck back soon\nDecember 31, 2026\nON SALE SOON Thanks!\nGALLERY\nDinosaur That Pooped\nDinosaur That Pooped\nDinosaur That Pooped\nDinosaur That Pooped\nDinosaur That Pooped\nDinosaur That Pooped\nDinosaur That Pooped\nDinosaur That Pooped\nDinosaur That Pooped\nDinosaur That Pooped\nCREATIVES\nTom Fletcher\nDougie Poynter\n© 2024 Tom Fletcher and Dougie Poynter\nSite byelate global."
}
